snapgpt/__init__.py
snapgpt/__main__.py
snapgpt/incremental.py
snapgpt/watch.py
snapgpt/cli/__init__.py
snapgpt/cli/commands.py
snapgpt/cli/config.py
snapgpt/cli/editor.py
snapgpt/cli/main.py
snapgpt/cli/parser.py
snapgpt-0.2.2.dist-info/LICENSE
snapgpt-0.2.2.dist-info/METADATA
snapgpt-0.2.2.dist-info/WHEEL
snapgpt-0.2.2.dist-info/entry_points.txt
snapgpt-0.2.2.dist-info/top_level.txt
snapgpt-0.2.2.dist-info/RECORD
