Metadata-Version: 2.1
Name: snapgpt
Version: 0.2.2
Summary: A tool to create readable snapshots of your codebase
Home-page: https://github.com/halfprice06/snapgpt
Author: Daniel Price
Author-email: 
License: MIT License
Project-URL: Homepage, https://github.com/halfprice06/snapgpt
Project-URL: Repository, https://github.com/halfprice06/snapgpt
Classifier: Development Status :: 4 - Beta
Classifier: Environment :: Console
Classifier: Intended Audience :: Developers
Classifier: License :: OSI Approved :: MIT License
Classifier: Operating System :: OS Independent
Classifier: Programming Language :: Python :: 3
Classifier: Programming Language :: Python :: 3.7
Classifier: Programming Language :: Python :: 3.8
Classifier: Programming Language :: Python :: 3.9
Classifier: Topic :: Software Development :: Libraries :: Python Modules
Requires-Python: >=3.7
License-File: LICENSE
Requires-Dist: pathlib
Requires-Dist: termcolor>=2.3.0
Requires-Dist: pyperclip>=1.8.2
Requires-Dist: watchdog>=2.1.0
Requires-Dist: markitdown
